LICENSE
MANIFEST.in
README.rst
setup.cfg
setup.py
versioneer.py
django_opentracing/__init__.py
django_opentracing/_version.py
django_opentracing/middleware.py
django_opentracing/tracing.py
signalfx_instrumentation_django.egg-info/PKG-INFO
signalfx_instrumentation_django.egg-info/SOURCES.txt
signalfx_instrumentation_django.egg-info/dependency_links.txt
signalfx_instrumentation_django.egg-info/requires.txt
signalfx_instrumentation_django.egg-info/top_level.txt
tests/manage.py